Metadata-Version: 2.1
Name: tap-salesforce
Version: 2.1.1
Summary: Singer.io tap for extracting data from the Salesforce API
Home-page: https://singer.io
Author: Stitch
Classifier: Programming Language :: Python :: 3 :: Only
License-File: LICENSE
Requires-Dist: requests==2.32.3
Requires-Dist: singer-python==5.13.0
Requires-Dist: xmltodict==0.11.0
